setup.py
plaid/__init__.py
plaid/client.py
plaid/errors.py
plaid/http.py
plaid/requester.py
plaid/utils.py
plaid/version.py
plaid_python_legacy.egg-info/PKG-INFO
plaid_python_legacy.egg-info/SOURCES.txt
plaid_python_legacy.egg-info/dependency_links.txt
plaid_python_legacy.egg-info/not-zip-safe
plaid_python_legacy.egg-info/requires.txt
plaid_python_legacy.egg-info/top_level.txt
tests/__init__.py
tests/integration/__init__.py
tests/integration/test_client.py
tests/unit/__init__.py
tests/unit/test_client.py