Metadata-Version: 1.1
Name: plaid-python-legacy
Version: 1.5.1
Summary: Python API client library for Plaid's legacy API
Home-page: https://github.com/plaid/plaid-python-legacy
Author: UNKNOWN
Author-email: UNKNOWN
License: MIT
Download-URL: https://github.com/plaid/plaid-python-legacy/tarball/v1.5.1
Keywords: api,client,plaid
Platform: UNKNOWN
Classifier: Programming Language :: Python
Classifier: Programming Language :: Python :: 2
Classifier: Programming Language :: Python :: 2.7
Classifier: Programming Language :: Python :: 3
Classifier: Programming Language :: Python :: 3.4
Classifier: Programming Language :: Python :: 3.5
Classifier: Topic :: Software Development :: Libraries :: Python Modules
Classifier: Environment :: Web Environment
